limix_legacy/__init__.py
limix_legacy/deprecated/__init__.py
limix_legacy/deprecated/_core.cpython-36m-darwin.so
limix_legacy/deprecated/core.py
limix_legacy/deprecated/io/__init__.py
limix_legacy/deprecated/io/conversion.py
limix_legacy/deprecated/io/data.py
limix_legacy/deprecated/io/data_util.py
limix_legacy/deprecated/io/genotype_reader.py
limix_legacy/deprecated/io/output_writer.py
limix_legacy/deprecated/io/phenotype_reader.py
limix_legacy/deprecated/io/plink.py
limix_legacy/deprecated/modules/BLUP.py
limix_legacy/deprecated/modules/__init__.py
limix_legacy/deprecated/modules/grm.py
limix_legacy/deprecated/modules/lmm_fast.py
limix_legacy/deprecated/modules/lmm_forest.py
limix_legacy/deprecated/modules/lmmlasso.py
limix_legacy/deprecated/modules/mixedForestUtils.py
limix_legacy/deprecated/modules/multiPanama.py
limix_legacy/deprecated/modules/panama.py
limix_legacy/deprecated/modules/parMixedForest.py
limix_legacy/deprecated/modules/pySplittingCore.py
limix_legacy/deprecated/modules/qtl.py
limix_legacy/deprecated/modules/varDecompSet.py
limix_legacy/deprecated/modules/varianceDecomposition.py
limix_legacy/deprecated/stats/__init__.py
limix_legacy/deprecated/stats/fdr.py
limix_legacy/deprecated/stats/geno_summary.py
limix_legacy/deprecated/stats/pca.py
limix_legacy/deprecated/stats/power.py
limix_legacy/deprecated/utils/__init__.py
limix_legacy/deprecated/utils/fastlmm.py
limix_legacy/deprecated/utils/plot.py
limix_legacy/deprecated/utils/preprocess.py
limix_legacy/ensemble/SplittingCore.cpython-36m-darwin.so
limix_legacy/ensemble/__init__.py
limix_legacy/ensemble/blup.py
limix_legacy/ensemble/lmm_fast.py
limix_legacy/ensemble/lmm_forest.py
limix_legacy/ensemble/lmm_forest_utils.py
limix_legacy/ensemble/par_lmm_forest.py
limix_legacy/ensemble/py_splitting_core.py
limix_legacy/io/__init__.py
limix_legacy/io/conversion.py
limix_legacy/io/data.py
limix_legacy/io/data_util.py
limix_legacy/io/genotype_reader.py
limix_legacy-0.8.12.dist-info/DESCRIPTION.rst
limix_legacy-0.8.12.dist-info/METADATA
limix_legacy-0.8.12.dist-info/RECORD
limix_legacy-0.8.12.dist-info/WHEEL
limix_legacy-0.8.12.dist-info/metadata.json
limix_legacy-0.8.12.dist-info/top_level.txt
