Metadata-Version: 2.0
Name: limix-legacy
Version: 0.8.12
Summary: A flexible and fast mixed model toolbox.
Home-page: https://github.com/limix/limix-legacy
Author: Limix Developers
Author-email: stegle@ebi.ac.uk
License: Apache License 2.0
Keywords: linear mixed models,GWAS,QTL,Variance component modelling
Platform: UNKNOWN
Classifier: Development Status :: 5 - Production/Stable
Classifier: Environment :: Console
Classifier: Intended Audience :: Science/Research
Classifier: License :: OSI Approved :: Apache Software License
Classifier: Natural Language :: English
Classifier: Programming Language :: Python :: 2.7
Classifier: Topic :: Scientific/Engineering :: Bio-Informatics
Requires-Dist: scikit-learn
Requires-Dist: pandas
Requires-Dist: scipy
Requires-Dist: h5py
Requires-Dist: numpy
